redit/__init__.py
redit/main.py
redit-1.0.2.dist-info/METADATA
redit-1.0.2.dist-info/WHEEL
redit-1.0.2.dist-info/entry_points.txt
redit-1.0.2.dist-info/top_level.txt
redit-1.0.2.dist-info/RECORD
