Metadata-Version: 2.1
Name: redit
Version: 1.0.2
Summary: Preview recently edited notes and launch editor
Home-page: https://github.com/pb-/redit
Author: Paul Baecher
License: UNKNOWN
Platform: UNKNOWN
